LICENSE
LICENSE.txt
librbdl.so.2.6.0
librbdl_urdfreader.so.2.6.0
rbdlp.cpython-310-x86_64-linux-gnu.so
rbdlp-2.6.0.dist-info/METADATA
rbdlp-2.6.0.dist-info/WHEEL
rbdlp-2.6.0.dist-info/top_level.txt
rbdlp-2.6.0.dist-info/RECORD
